LICENSE
README.md
setup.py
exec_utils/__init__.py
exec_utils/burper.py
exec_utils/exec_strict_direct.py
exec_utils/exec_strict_error.py
exec_utils/exec_utils.py
exec_utils/slurper.py
exec_utils.egg-info/PKG-INFO
exec_utils.egg-info/SOURCES.txt
exec_utils.egg-info/dependency_links.txt
exec_utils.egg-info/top_level.txt