Metadata-Version: 1.0
Name: exec-utils
Version: 0.1.1
Summary: Versatile utility to execute commands
Home-page: UNKNOWN
Author: Reto Schuettel
Author-email: reto.schuettel@ergon.ch
License: MIT
Platform: UNKNOWN
